llama_index/tools/vectara_query/__init__.py
llama_index/tools/vectara_query/base.py
llama_index_tools_vectara_query-0.4.1.dist-info/METADATA
llama_index_tools_vectara_query-0.4.1.dist-info/WHEEL
llama_index_tools_vectara_query-0.4.1.dist-info/licenses/LICENSE
llama_index_tools_vectara_query-0.4.1.dist-info/RECORD
