Metadata-Version: 2.4
Name: llama-index-tools-vectara-query
Version: 0.4.1
Summary: llama-index tools vectara query integration
Author-email: David Oplatka <david.oplatka@vectara.com>
License-Expression: MIT
License-File: LICENSE
Requires-Python: <4.0,>=3.9
Requires-Dist: llama-index-core<0.15,>=0.13.0
Requires-Dist: llama-index-indices-managed-vectara<0.6,>=0.5.0
